starfish_api_client/__init__.py
starfish_api_client/client.py
starfish_api_client-0.1.0.dist-info/LICENSE
starfish_api_client-0.1.0.dist-info/METADATA
starfish_api_client-0.1.0.dist-info/WHEEL
starfish_api_client-0.1.0.dist-info/RECORD
